django_start_tool/__init__.py
django_start_tool/handler.py
django_start_tool/utils.py
django_start_tool/cli/main.py
django_start_tool/template/manage.py-tpl
django_start_tool/template/project_name/__init__.py
django_start_tool/template/project_name/asgi.py-tpl
django_start_tool/template/project_name/settings.py-tpl
django_start_tool/template/project_name/urls.py
django_start_tool/template/project_name/wsgi.py-tpl
django_start_tool-1.0.1.dist-info/LICENSE
django_start_tool-1.0.1.dist-info/METADATA
django_start_tool-1.0.1.dist-info/WHEEL
django_start_tool-1.0.1.dist-info/entry_points.txt
django_start_tool-1.0.1.dist-info/top_level.txt
django_start_tool-1.0.1.dist-info/RECORD
