Metadata-Version: 2.1
Name: django-start-tool
Version: 1.0.1
Summary: A full-featured CLI for quickly creating django projects.
Home-page: UNKNOWN
Author: Georgy Gnezdilov
Author-email: georgy.gnezdilov@gmail.com
License: MIT
Project-URL: Source, https://github.com/solarless/django-start-tool
Platform: UNKNOWN
Classifier: Environment :: Console
Classifier: Intended Audience :: Developers
Classifier: License :: OSI Approved :: MIT License
Classifier: Operating System :: OS Independent
Classifier: Programming Language :: Python
Classifier: Programming Language :: Python :: 3
Classifier: Programming Language :: Python :: 3 :: Only
Classifier: Programming Language :: Python :: 3.10
Requires-Python: >=3.10
License-File: LICENSE
Requires-Dist: jinja2 (>=3.1.2)
Requires-Dist: markupsafe (>=2.1.1)
